markey/__init__.py
markey/_compat.py
markey/machine.py
markey/rules.py
markey/tools.py
markey/underscore.py
markey-0.8.dist-info/DESCRIPTION.rst
markey-0.8.dist-info/METADATA
markey-0.8.dist-info/RECORD
markey-0.8.dist-info/WHEEL
markey-0.8.dist-info/metadata.json
markey-0.8.dist-info/top_level.txt
